django_fretboard-1.17.6.dist-info/METADATA
django_fretboard-1.17.6.dist-info/RECORD
django_fretboard-1.17.6.dist-info/WHEEL
django_fretboard-1.17.6.dist-info/top_level.txt
fretboard/__init__.py
fretboard/admin.py
fretboard/filters.py
fretboard/forms.py
fretboard/helpers.py
fretboard/managers.py
fretboard/models.py
fretboard/settings.py
fretboard/signals.py
fretboard/tests.py
fretboard/urls.py
fretboard/static/fretboard/fretboard.css
fretboard/static/fretboard/fretboard.js
fretboard/static/libs/highlight.js
fretboard/static/libs/lscache.js
fretboard/templates/base.html
fretboard/templates/fretboard/add_edit.html
fretboard/templates/fretboard/base.html
fretboard/templates/fretboard/category_list.html
fretboard/templates/fretboard/filter_results.html
fretboard/templates/fretboard/post_wrapper.html
fretboard/templates/fretboard/topic_wrapper.html
fretboard/templates/fretboard/includes/base_nav.html
fretboard/templates/fretboard/includes/paginator.html
fretboard/templates/fretboard/includes/post_form.html
fretboard/templates/fretboard/includes/post_list.html
fretboard/templates/fretboard/includes/post_single.html
fretboard/templates/fretboard/includes/topic_list.html
fretboard/templates/fretboard/includes/topic_quick_links.html
fretboard/templates/fretboard/utils/move_topic.html
fretboard/templatetags/__init__.py
fretboard/templatetags/fretboard_tags.py
fretboard/templatetags/paginator.py
fretboard/templatetags/truncatechars.py
fretboard/test_templates/fretboard/add_edit.html
fretboard/test_templates/fretboard/base.html
fretboard/test_templates/fretboard/category_list.html
fretboard/test_templates/fretboard/filter_results.html
fretboard/test_templates/fretboard/post_wrapper.html
fretboard/test_templates/fretboard/topic_wrapper.html
fretboard/test_templates/fretboard/includes/base_nav.html
fretboard/test_templates/fretboard/includes/paginator.html
fretboard/test_templates/fretboard/includes/post_form.html
fretboard/test_templates/fretboard/includes/post_list.html
fretboard/test_templates/fretboard/includes/post_single.html
fretboard/test_templates/fretboard/includes/topic_list.html
