Metadata-Version: 2.1
Name: django-fretboard
Version: 1.17.6
Summary: Responsive, powerful, simple Django forums.
Home-page: http://github.com/tBaxter/django-fretboard
Author: Tim Baxter
Author-email: mail.baxter@gmail.com
License: MIT
Platform: UNKNOWN
Requires-Dist: tango-shared-core (>=1.5)
Requires-Dist: tango-voting (>=0.4)
Requires-Dist: django (>=2.0)
Requires-Dist: jinja2
Requires-Dist: django-typogrify
